torque/__init__.py
torque/__main__.py
torque/base.py
torque/client.py
torque/constants.py
torque/environments.py
torque/exceptions.py
torque/session.py
torque/shell.py
torque/utils.py
torque/branch/__init__.py
torque/branch/branch_context.py
torque/branch/branch_utils.py
torque/commands/__init__.py
torque/commands/base.py
torque/commands/bp.py
torque/commands/configure.py
torque/commands/env.py
torque/models/__init__.py
torque/models/blueprints.py
torque/models/connection.py
torque/parsers/__init__.py
torque/parsers/command_input_parsers.py
torque/parsers/command_input_validators.py
torque/parsers/global_input_parser.py
torque/services/__init__.py
torque/services/config.py
torque/services/connection.py
torque/services/output_formatter.py
torque/services/sb_naming.py
torque/services/version.py
torque/services/waiter.py
torque/view/__init__.py
torque/view/configure_list_view.py
torque/view/view_helper.py
torque_cli-1.8.1.dist-info/LICENSE
torque_cli-1.8.1.dist-info/METADATA
torque_cli-1.8.1.dist-info/WHEEL
torque_cli-1.8.1.dist-info/entry_points.txt
torque_cli-1.8.1.dist-info/top_level.txt
torque_cli-1.8.1.dist-info/RECORD
