Metadata-Version: 2.1
Name: torque-cli
Version: 1.8.1
Summary: A command line interface for torque
Home-page: https://www.quali.com/
Author: Quali
Author-email: support@qualisystems.com
License: Apache Software License
Keywords: torque environment cloud cloudshell quali command-line cli
Platform: UNKNOWN
Classifier: Development Status :: 4 - Beta
Classifier: Intended Audience :: Developers
Classifier: Topic :: Software Development :: User Interfaces
Classifier: Programming Language :: Python :: 3.6
Classifier: Programming Language :: Python :: 3.7
Classifier: Programming Language :: Python :: 3.8
Requires-Python: >=3.6
Requires-Dist: docopt (==0.6.2)
Requires-Dist: requests (==2.25.1)
Requires-Dist: setuptools (==54.2.0)
Requires-Dist: gitpython (==3.1.12)
Requires-Dist: pyyaml (==5.4.1)
Requires-Dist: tabulate (==0.8.9)
Requires-Dist: colorama (==0.4.3)
Requires-Dist: yaspin (==1.4.1)
Requires-Dist: semantic-version (==2.8.5)
